[
    {
        "supplierType": "demolitionWalls",
        "baseType": "demolitionWalls",
        "newBuildings": false,
        "repairReplace": true,
        "hasMinMaxDimensions": false,
        "createdOn": "2025-08-07T11:52:56Z",
        "id": "00120efc-6755-4d82-be0c-01c7f05c1ce9",
        "updatedOn": "2025-08-07T11:54:18Z",
        "owner": "85839425-0cfe-471f-94da-e4086b1dc961"
    },
    {
        "supplierType": "demolitionCladding",
        "baseType": "demolitionCladding",
        "newBuildings": false,
        "repairReplace": true,
        "hasMinMaxDimensions": false,
        "createdOn": "2025-08-07T11:52:56Z",
        "id": "0168e261-1681-433c-b0b4-95aca95ce9e2",
        "updatedOn": "2025-08-07T11:54:18Z",
        "owner": "85839425-0cfe-471f-94da-e4086b1dc961"
    },
    {
        "supplierType": "quantitySurveyorInstall",
        "baseType": "quantitySurveyor",
        "newBuildings": true,
        "repairReplace": false,
        "hasMinMaxDimensions": false,
        "createdOn": "2025-08-07T11:52:56Z",
        "id": "037573e2-4f87-4d66-963c-220eed3aa51b",
        "updatedOn": "2025-08-07T11:54:15Z",
        "owner": "85839425-0cfe-471f-94da-e4086b1dc961"
    },
    {
        "supplierType": "concreteBlockInstall",
        "baseType": "concreteBlock",
        "newBuildings": true,
        "repairReplace": false,
        "hasMinMaxDimensions": false,
        "createdOn": "2025-08-07T11:52:56Z",
        "id": "07fa394f-ead3-4074-b216-429284ee3a20",
        "updatedOn": "2025-08-07T11:54:15Z",
        "owner": "85839425-0cfe-471f-94da-e4086b1dc961"
    },
    {
        "supplierType": "roofSupplyAndInstall",
        "baseType": "roof",
        "newBuildings": true,
        "repairReplace": false,
        "hasMinMaxDimensions": true,
        "createdOn": "2025-08-07T11:52:56Z",
        "id": "106c3dcc-54f0-4b07-b3b7-7471f034d8a6",
        "updatedOn": "2025-08-16T11:15:05Z",
        "owner": "85839425-0cfe-471f-94da-e4086b1dc961"
    },
    {
        "supplierType": "roofRepairSupply",
        "baseType": "roofRepair",
        "newBuildings": false,
        "repairReplace": true,
        "hasMinMaxDimensions": true,
        "createdOn": "2025-08-07T11:52:56Z",
        "id": "139b198c-1674-4806-b500-f0b53824cb38",
        "updatedOn": "2025-08-16T11:15:06Z",
        "owner": "85839425-0cfe-471f-94da-e4086b1dc961"
    },
    {
        "supplierType": "steelFabricatorSupplyAndInstall",
        "baseType": "steelFabricator",
        "newBuildings": true,
        "repairReplace": false,
        "hasMinMaxDimensions": true,
        "createdOn": "2025-08-07T11:52:56Z",
        "id": "13b17142-dadc-449c-ab48-8147d6b34d1a",
        "updatedOn": "2025-08-16T11:15:03Z",
        "owner": "85839425-0cfe-471f-94da-e4086b1dc961"
    },
    {
        "supplierType": "solarPanelSupply",
        "baseType": "solarPanel",
        "newBuildings": true,
        "repairReplace": false,
        "hasMinMaxDimensions": false,
        "createdOn": "2025-08-07T11:52:56Z",
        "id": "14f0e09e-3927-4eec-9e51-9bcb9c23c8ba",
        "updatedOn": "2025-08-07T11:54:15Z",
        "owner": "85839425-0cfe-471f-94da-e4086b1dc961"
    },
    {
        "supplierType": "polytunnelSupplyAndInstall",
        "baseType": "polytunnel",
        "newBuildings": true,
        "repairReplace": false,
        "hasMinMaxDimensions": true,
        "createdOn": "2025-08-07T11:52:56Z",
        "id": "1ca4f3bd-8e99-4025-bcd9-816b310062e3",
        "updatedOn": "2025-08-16T11:15:19Z",
        "owner": "85839425-0cfe-471f-94da-e4086b1dc961"
    },
    {
        "supplierType": "polytunnelSupply",
        "baseType": "polytunnel",
        "newBuildings": true,
        "repairReplace": false,
        "hasMinMaxDimensions": true,
        "createdOn": "2025-08-07T11:52:56Z",
        "id": "2fcfdb5f-af26-4dc1-be66-22cf97c09487",
        "updatedOn": "2025-08-16T11:15:17Z",
        "owner": "85839425-0cfe-471f-94da-e4086b1dc961"
    },
    {
        "supplierType": "demolitionRoof",
        "baseType": "demolitionRoof",
        "newBuildings": false,
        "repairReplace": true,
        "hasMinMaxDimensions": false,
        "createdOn": "2025-08-07T11:52:56Z",
        "id": "37ffabed-805e-4b47-8b30-e732d91c0d46",
        "updatedOn": "2025-08-07T11:54:18Z",
        "owner": "85839425-0cfe-471f-94da-e4086b1dc961"
    },
    {
        "supplierType": "concreteWallRepairSupplyAndInstall",
        "baseType": "concreteWallRepair",
        "newBuildings": false,
        "repairReplace": true,
        "hasMinMaxDimensions": false,
        "createdOn": "2025-08-07T11:52:56Z",
        "id": "39264231-727a-4815-ac47-edf2b403e0f5",
        "updatedOn": "2025-08-07T11:54:18Z",
        "owner": "85839425-0cfe-471f-94da-e4086b1dc961"
    },
    {
        "supplierType": "massConcreteSupplyAndInstall",
        "baseType": "massConcrete",
        "newBuildings": true,
        "repairReplace": false,
        "hasMinMaxDimensions": false,
        "createdOn": "2025-08-07T11:52:56Z",
        "id": "3d216047-0b1d-4dd0-a402-c2443b87330d",
        "updatedOn": "2025-08-07T11:54:15Z",
        "owner": "85839425-0cfe-471f-94da-e4086b1dc961"
    },
    {
        "supplierType": "roofInstall",
        "baseType": "roof",
        "newBuildings": true,
        "repairReplace": false,
        "hasMinMaxDimensions": true,
        "createdOn": "2025-08-07T11:52:56Z",
        "id": "3f7c8167-3383-462b-b793-8e5c94bae7db",
        "updatedOn": "2025-08-16T11:15:05Z",
        "owner": "85839425-0cfe-471f-94da-e4086b1dc961"
    },
    {
        "supplierType": "concreteBlockSupply",
        "baseType": "concreteBlock",
        "newBuildings": true,
        "repairReplace": false,
        "hasMinMaxDimensions": false,
        "createdOn": "2025-08-07T11:52:56Z",
        "id": "3fa48b59-192e-45cd-aed6-14718a6222af",
        "updatedOn": "2025-08-07T11:54:15Z",
        "owner": "85839425-0cfe-471f-94da-e4086b1dc961"
    },
    {
        "supplierType": "steelErectorSupplyAndInstall",
        "baseType": "steelErector",
        "newBuildings": true,
        "repairReplace": false,
        "hasMinMaxDimensions": true,
        "createdOn": "2025-08-07T11:52:56Z",
        "id": "4234c996-b1a3-4942-afcd-60da2aa6da80",
        "updatedOn": "2025-08-16T11:15:00Z",
        "owner": "85839425-0cfe-471f-94da-e4086b1dc961"
    },
    {
        "supplierType": "solarPanelInstall",
        "baseType": "solarPanel",
        "newBuildings": true,
        "repairReplace": false,
        "hasMinMaxDimensions": false,
        "createdOn": "2025-08-07T11:52:56Z",
        "id": "42f1207d-4f1e-4702-876a-4d9dac76c9ba",
        "updatedOn": "2025-08-07T11:54:15Z",
        "owner": "85839425-0cfe-471f-94da-e4086b1dc961"
    },
    {
        "supplierType": "cattleSheetDoorSupplyAndInstall",
        "baseType": "cattleSheetDoor",
        "newBuildings": true,
        "repairReplace": false,
        "hasMinMaxDimensions": false,
        "createdOn": "2025-08-07T11:52:56Z",
        "id": "4726d784-19af-4cce-bea0-3464354be348",
        "updatedOn": "2025-08-07T11:54:15Z",
        "owner": "85839425-0cfe-471f-94da-e4086b1dc961"
    },
    {
        "supplierType": "quantitySurveyorSupply",
        "baseType": "quantitySurveyor",
        "newBuildings": true,
        "repairReplace": false,
        "hasMinMaxDimensions": false,
        "createdOn": "2025-08-07T11:52:56Z",
        "id": "47fa8605-6c08-4b87-ae6b-d8e1218e1a40",
        "updatedOn": "2025-08-07T11:54:15Z",
        "owner": "85839425-0cfe-471f-94da-e4086b1dc961"
    },
    {
        "supplierType": "polytunnelInstall",
        "baseType": "polytunnel",
        "newBuildings": true,
        "repairReplace": false,
        "hasMinMaxDimensions": true,
        "createdOn": "2025-08-07T11:52:56Z",
        "id": "4c378bea-e668-4bdb-90cf-465cf86f159a",
        "updatedOn": "2025-08-16T11:15:18Z",
        "owner": "85839425-0cfe-471f-94da-e4086b1dc961"
    },
    {
        "supplierType": "concreteBlockSupplyAndInstall",
        "baseType": "concreteBlock",
        "newBuildings": true,
        "repairReplace": false,
        "hasMinMaxDimensions": false,
        "createdOn": "2025-08-07T11:52:56Z",
        "id": "4f0987ed-944d-4bc9-a7dc-a1f9ae23a1c1",
        "updatedOn": "2025-08-07T11:54:15Z",
        "owner": "85839425-0cfe-471f-94da-e4086b1dc961"
    },
    {
        "supplierType": "demolitionStructures",
        "baseType": "demolitionStructures",
        "newBuildings": false,
        "repairReplace": true,
        "hasMinMaxDimensions": false,
        "createdOn": "2025-08-07T11:52:56Z",
        "id": "5941c7a8-46bc-48bc-ba99-6e123ef1b651",
        "updatedOn": "2025-08-07T11:54:18Z",
        "owner": "85839425-0cfe-471f-94da-e4086b1dc961"
    },
    {
        "supplierType": "concreteFloorSupplyAndInstall",
        "baseType": "concreteFloor",
        "newBuildings": true,
        "repairReplace": false,
        "hasMinMaxDimensions": false,
        "createdOn": "2025-08-07T11:52:56Z",
        "id": "5b3f2390-ec76-4d1a-8461-32f562c86dd0",
        "updatedOn": "2025-08-07T11:54:15Z",
        "owner": "85839425-0cfe-471f-94da-e4086b1dc961"
    },
    {
        "supplierType": "groundWorkerSupply",
        "baseType": "groundWorker",
        "newBuildings": true,
        "repairReplace": false,
        "hasMinMaxDimensions": false,
        "createdOn": "2025-08-07T11:52:56Z",
        "id": "5e16b3d2-07b1-4356-a9d7-dd8329adb217",
        "updatedOn": "2025-08-07T11:54:15Z",
        "owner": "85839425-0cfe-471f-94da-e4086b1dc961"
    },
    {
        "supplierType": "steelErectorSupply",
        "baseType": "steelErector",
        "newBuildings": true,
        "repairReplace": false,
        "hasMinMaxDimensions": true,
        "createdOn": "2025-08-07T11:52:56Z",
        "id": "650b26f1-59d3-42b5-b1ae-5aadad3cbd30",
        "updatedOn": "2025-08-16T11:14:58Z",
        "owner": "85839425-0cfe-471f-94da-e4086b1dc961"
    },
    {
        "supplierType": "rainwaterHarvestingSupply",
        "baseType": "rainwaterHarvesting",
        "newBuildings": true,
        "repairReplace": false,
        "hasMinMaxDimensions": false,
        "createdOn": "2025-08-07T11:52:56Z",
        "id": "6d196f02-bf6f-4ba1-95f3-ed2a8f361cbf",
        "updatedOn": "2025-08-07T11:54:15Z",
        "owner": "85839425-0cfe-471f-94da-e4086b1dc961"
    },
    {
        "supplierType": "claddingRepairInstall",
        "baseType": "claddingRepair",
        "newBuildings": false,
        "repairReplace": true,
        "hasMinMaxDimensions": false,
        "createdOn": "2025-08-07T11:52:56Z",
        "id": "717fdf44-c6f5-4c4a-a74f-90b78b5ac1d3",
        "updatedOn": "2025-08-07T11:54:15Z",
        "owner": "85839425-0cfe-471f-94da-e4086b1dc961"
    },
    {
        "supplierType": "concretePanelSupply",
        "baseType": "concretePanel",
        "newBuildings": true,
        "repairReplace": false,
        "hasMinMaxDimensions": false,
        "createdOn": "2025-08-07T11:52:56Z",
        "id": "73526a31-ff46-4087-afb5-f9922434a6c6",
        "updatedOn": "2025-08-07T11:54:15Z",
        "owner": "85839425-0cfe-471f-94da-e4086b1dc961"
    },
    {
        "supplierType": "roofRepairSupplyAndInstall",
        "baseType": "roofRepair",
        "newBuildings": false,
        "repairReplace": true,
        "hasMinMaxDimensions": true,
        "createdOn": "2025-08-07T11:52:56Z",
        "id": "7497944a-ee60-4490-b9d1-3a14e677e698",
        "updatedOn": "2025-08-16T11:15:08Z",
        "owner": "85839425-0cfe-471f-94da-e4086b1dc961"
    },
    {
        "supplierType": "cattleSheetDoorSupply",
        "baseType": "cattleSheetDoor",
        "newBuildings": true,
        "repairReplace": false,
        "hasMinMaxDimensions": false,
        "createdOn": "2025-08-07T11:52:56Z",
        "id": "79ee8b94-4c00-4b32-972c-bd18d1d524ee",
        "updatedOn": "2025-08-07T11:54:15Z",
        "owner": "85839425-0cfe-471f-94da-e4086b1dc961"
    },
    {
        "supplierType": "claddingRepairSupplyAndInstall",
        "baseType": "claddingRepair",
        "newBuildings": false,
        "repairReplace": true,
        "hasMinMaxDimensions": false,
        "createdOn": "2025-08-07T11:52:56Z",
        "id": "7ba0120e-4004-418c-90d3-54314450b252",
        "updatedOn": "2025-08-07T11:54:15Z",
        "owner": "85839425-0cfe-471f-94da-e4086b1dc961"
    },
    {
        "supplierType": "rainwaterHarvestingSupplyAndInstall",
        "baseType": "rainwaterHarvesting",
        "newBuildings": true,
        "repairReplace": false,
        "hasMinMaxDimensions": false,
        "createdOn": "2025-08-07T11:52:56Z",
        "id": "7d8bc2ef-fd61-4183-917e-99e018523d33",
        "updatedOn": "2025-08-07T11:54:15Z",
        "owner": "85839425-0cfe-471f-94da-e4086b1dc961"
    },
    {
        "supplierType": "gutteringSupplyAndInstall",
        "baseType": "guttering",
        "newBuildings": true,
        "repairReplace": false,
        "hasMinMaxDimensions": false,
        "createdOn": "2025-08-07T11:52:56Z",
        "id": "8128f7e0-b69b-4938-bfe9-a6ac328bdfe0",
        "updatedOn": "2025-08-07T11:54:15Z",
        "owner": "85839425-0cfe-471f-94da-e4086b1dc961"
    },
    {
        "supplierType": "gutteringRepairInstall",
        "baseType": "gutteringRepair",
        "newBuildings": false,
        "repairReplace": true,
        "hasMinMaxDimensions": false,
        "createdOn": "2025-08-07T11:52:56Z",
        "id": "83fda7c9-2d4d-4f26-a92a-28878f4e78bd",
        "updatedOn": "2025-08-07T11:54:16Z",
        "owner": "85839425-0cfe-471f-94da-e4086b1dc961"
    },
    {
        "supplierType": "claddingRepairSupply",
        "baseType": "claddingRepair",
        "newBuildings": false,
        "repairReplace": true,
        "hasMinMaxDimensions": false,
        "createdOn": "2025-08-07T11:52:56Z",
        "id": "87b9dd42-9de5-4dd0-b065-4611f35d6a26",
        "updatedOn": "2025-08-07T11:54:15Z",
        "owner": "85839425-0cfe-471f-94da-e4086b1dc961"
    },
    {
        "supplierType": "roofSupply",
        "baseType": "roof",
        "newBuildings": true,
        "repairReplace": false,
        "hasMinMaxDimensions": true,
        "createdOn": "2025-08-07T11:52:56Z",
        "id": "883a9c87-8e51-4544-a597-c9e66df41315",
        "updatedOn": "2025-08-16T11:15:04Z",
        "owner": "85839425-0cfe-471f-94da-e4086b1dc961"
    },
    {
        "supplierType": "solarPanelSupplyAndInstall",
        "baseType": "solarPanel",
        "newBuildings": true,
        "repairReplace": false,
        "hasMinMaxDimensions": false,
        "createdOn": "2025-08-07T11:52:56Z",
        "id": "8b122083-3a3c-44db-a392-5cd1c6593722",
        "updatedOn": "2025-08-07T11:54:15Z",
        "owner": "85839425-0cfe-471f-94da-e4086b1dc961"
    },
    {
        "supplierType": "concreteFloorSupply",
        "baseType": "concreteFloor",
        "newBuildings": true,
        "repairReplace": false,
        "hasMinMaxDimensions": false,
        "createdOn": "2025-08-07T11:52:56Z",
        "id": "90b25bdf-b189-453c-a570-f1d3d9b4d017",
        "updatedOn": "2025-08-07T11:54:15Z",
        "owner": "85839425-0cfe-471f-94da-e4086b1dc961"
    },
    {
        "supplierType": "concreteWallRepairSupply",
        "baseType": "concreteWallRepair",
        "newBuildings": false,
        "repairReplace": true,
        "hasMinMaxDimensions": false,
        "createdOn": "2025-08-07T11:52:56Z",
        "id": "92c7f160-2cda-478f-a4af-3d245e0fd0ae",
        "updatedOn": "2025-08-07T11:54:18Z",
        "owner": "85839425-0cfe-471f-94da-e4086b1dc961"
    },
    {
        "supplierType": "claddingSupplyAndInstall",
        "baseType": "cladding",
        "newBuildings": true,
        "repairReplace": false,
        "hasMinMaxDimensions": false,
        "createdOn": "2025-08-07T11:52:56Z",
        "id": "9716c65e-bb63-486f-b517-5551784abc07",
        "updatedOn": "2025-08-07T11:54:15Z",
        "owner": "85839425-0cfe-471f-94da-e4086b1dc961"
    },
    {
        "supplierType": "groundWorkerInstall",
        "baseType": "groundWorker",
        "newBuildings": true,
        "repairReplace": false,
        "hasMinMaxDimensions": false,
        "createdOn": "2025-08-07T11:52:56Z",
        "id": "974d026b-25a7-4986-bc24-f8085aba073d",
        "updatedOn": "2025-08-07T11:54:15Z",
        "owner": "85839425-0cfe-471f-94da-e4086b1dc961"
    },
    {
        "supplierType": "concretePanelInstall",
        "baseType": "concretePanel",
        "newBuildings": true,
        "repairReplace": false,
        "hasMinMaxDimensions": false,
        "createdOn": "2025-08-07T11:52:56Z",
        "id": "974fa302-ee8d-4ab7-8c78-c58c4f673b54",
        "updatedOn": "2025-08-07T11:54:15Z",
        "owner": "85839425-0cfe-471f-94da-e4086b1dc961"
    },
    {
        "supplierType": "gutteringRepairSupply",
        "baseType": "gutteringRepair",
        "newBuildings": false,
        "repairReplace": true,
        "hasMinMaxDimensions": false,
        "createdOn": "2025-08-07T11:52:56Z",
        "id": "9e8e57af-fe56-4961-82db-9637993bf7b8",
        "updatedOn": "2025-08-07T11:54:16Z",
        "owner": "85839425-0cfe-471f-94da-e4086b1dc961"
    },
    {
        "supplierType": "gutteringRepairSupplyAndInstall",
        "baseType": "gutteringRepair",
        "newBuildings": false,
        "repairReplace": true,
        "hasMinMaxDimensions": false,
        "createdOn": "2025-08-07T11:52:56Z",
        "id": "a4477e41-e087-408a-a735-9e5a97198ef7",
        "updatedOn": "2025-08-07T11:54:16Z",
        "owner": "85839425-0cfe-471f-94da-e4086b1dc961"
    },
    {
        "supplierType": "massConcreteInstall",
        "baseType": "massConcrete",
        "newBuildings": true,
        "repairReplace": false,
        "hasMinMaxDimensions": false,
        "createdOn": "2025-08-07T11:52:56Z",
        "id": "a7368a49-2cb2-4cfc-8cf6-ad5d69058934",
        "updatedOn": "2025-08-07T11:54:15Z",
        "owner": "85839425-0cfe-471f-94da-e4086b1dc961"
    },
    {
        "supplierType": "rainwaterHarvestingInstall",
        "baseType": "rainwaterHarvesting",
        "newBuildings": true,
        "repairReplace": false,
        "hasMinMaxDimensions": false,
        "createdOn": "2025-08-07T11:52:56Z",
        "id": "a8e60190-ef8e-4f0a-b819-67da0a10f0b6",
        "updatedOn": "2025-08-07T11:54:15Z",
        "owner": "85839425-0cfe-471f-94da-e4086b1dc961"
    },
    {
        "supplierType": "doorSupplyAndInstall",
        "baseType": "door",
        "newBuildings": true,
        "repairReplace": false,
        "hasMinMaxDimensions": false,
        "createdOn": "2025-08-07T11:52:56Z",
        "id": "b6e10682-552b-49e9-9e25-12e5dde62b91",
        "updatedOn": "2025-08-07T11:54:15Z",
        "owner": "85839425-0cfe-471f-94da-e4086b1dc961"
    },
    {
        "supplierType": "massConcreteSupply",
        "baseType": "massConcrete",
        "newBuildings": true,
        "repairReplace": false,
        "hasMinMaxDimensions": false,
        "createdOn": "2025-08-07T11:52:56Z",
        "id": "b8543e28-cee3-4eb8-82a3-7be84ba77190",
        "updatedOn": "2025-08-07T11:54:15Z",
        "owner": "85839425-0cfe-471f-94da-e4086b1dc961"
    },
    {
        "supplierType": "gutteringSupply",
        "baseType": "guttering",
        "newBuildings": true,
        "repairReplace": false,
        "hasMinMaxDimensions": false,
        "createdOn": "2025-08-07T11:52:56Z",
        "id": "bd7416c3-a12d-4c8c-9f0a-87df69f68a46",
        "updatedOn": "2025-08-07T11:54:15Z",
        "owner": "85839425-0cfe-471f-94da-e4086b1dc961"
    },
    {
        "supplierType": "doorSupply",
        "baseType": "door",
        "newBuildings": true,
        "repairReplace": false,
        "hasMinMaxDimensions": false,
        "createdOn": "2025-08-07T11:52:56Z",
        "id": "c7578026-f549-4f81-b06f-2fdda5575ac2",
        "updatedOn": "2025-08-07T11:54:15Z",
        "owner": "85839425-0cfe-471f-94da-e4086b1dc961"
    },
    {
        "supplierType": "groundWorkerSupplyAndInstall",
        "baseType": "groundWorker",
        "newBuildings": true,
        "repairReplace": false,
        "hasMinMaxDimensions": false,
        "createdOn": "2025-08-07T11:52:56Z",
        "id": "dfd5d5c5-d50a-4437-af66-331a9e99fe66",
        "updatedOn": "2025-08-07T11:54:15Z",
        "owner": "85839425-0cfe-471f-94da-e4086b1dc961"
    },
    {
        "supplierType": "steelFabricatorInstall",
        "baseType": "steelFabricator",
        "newBuildings": true,
        "repairReplace": false,
        "hasMinMaxDimensions": true,
        "createdOn": "2025-08-07T11:52:56Z",
        "id": "e5cc213a-3ada-4d57-950f-fca0613dc825",
        "updatedOn": "2025-08-16T11:15:02Z",
        "owner": "85839425-0cfe-471f-94da-e4086b1dc961"
    },
    {
        "supplierType": "steelErectorInstall",
        "baseType": "steelErector",
        "newBuildings": true,
        "repairReplace": false,
        "hasMinMaxDimensions": true,
        "createdOn": "2025-08-07T11:52:56Z",
        "id": "ebdc3065-7d12-40f2-8dd7-214b6d74048c",
        "updatedOn": "2025-08-16T11:14:59Z",
        "owner": "85839425-0cfe-471f-94da-e4086b1dc961"
    },
    {
        "supplierType": "concretePanelSupplyAndInstall",
        "baseType": "concretePanel",
        "newBuildings": true,
        "repairReplace": false,
        "hasMinMaxDimensions": false,
        "createdOn": "2025-08-07T11:52:56Z",
        "id": "ecd15e41-d475-4843-ab6c-20e4011a2f87",
        "updatedOn": "2025-08-07T11:54:15Z",
        "owner": "85839425-0cfe-471f-94da-e4086b1dc961"
    },
    {
        "supplierType": "concreteFloorInstall",
        "baseType": "concreteFloor",
        "newBuildings": true,
        "repairReplace": false,
        "hasMinMaxDimensions": false,
        "createdOn": "2025-08-07T11:52:56Z",
        "id": "eddc6593-244e-4f6d-a3c9-a6233fcf8958",
        "updatedOn": "2025-08-07T11:54:15Z",
        "owner": "85839425-0cfe-471f-94da-e4086b1dc961"
    },
    {
        "supplierType": "steelFabricatorSupply",
        "baseType": "steelFabricator",
        "newBuildings": true,
        "repairReplace": false,
        "hasMinMaxDimensions": true,
        "createdOn": "2025-08-07T11:52:56Z",
        "id": "f22e9520-2483-4ff2-913e-3dc5a13431e6",
        "updatedOn": "2025-08-16T11:15:01Z",
        "owner": "85839425-0cfe-471f-94da-e4086b1dc961"
    },
    {
        "supplierType": "doorInstall",
        "baseType": "door",
        "newBuildings": true,
        "repairReplace": false,
        "hasMinMaxDimensions": false,
        "createdOn": "2025-08-07T11:52:56Z",
        "id": "f2635fa9-ff4e-4a08-8cf6-80e7970bb5c5",
        "updatedOn": "2025-08-07T11:54:15Z",
        "owner": "85839425-0cfe-471f-94da-e4086b1dc961"
    },
    {
        "supplierType": "demolitionConcrete",
        "baseType": "demolitionConcrete",
        "newBuildings": false,
        "repairReplace": true,
        "hasMinMaxDimensions": false,
        "createdOn": "2025-08-07T11:52:56Z",
        "id": "f2c30d35-8255-482e-8d5f-15554c2fe0c1",
        "updatedOn": "2025-08-07T11:54:18Z",
        "owner": "85839425-0cfe-471f-94da-e4086b1dc961"
    },
    {
        "supplierType": "cattleSheetDoorInstall",
        "baseType": "cattleSheetDoor",
        "newBuildings": true,
        "repairReplace": false,
        "hasMinMaxDimensions": false,
        "createdOn": "2025-08-07T11:52:56Z",
        "id": "f807e972-0539-47a5-9a79-dd74a3e15982",
        "updatedOn": "2025-08-07T11:54:15Z",
        "owner": "85839425-0cfe-471f-94da-e4086b1dc961"
    },
    {
        "supplierType": "roofRepairInstall",
        "baseType": "roofRepair",
        "newBuildings": false,
        "repairReplace": true,
        "hasMinMaxDimensions": true,
        "createdOn": "2025-08-07T11:52:56Z",
        "id": "f8394ffb-fa72-42fc-86ed-38711dc1466f",
        "updatedOn": "2025-08-16T11:15:07Z",
        "owner": "85839425-0cfe-471f-94da-e4086b1dc961"
    },
    {
        "supplierType": "claddingSupply",
        "baseType": "cladding",
        "newBuildings": true,
        "repairReplace": false,
        "hasMinMaxDimensions": false,
        "createdOn": "2025-08-07T11:52:56Z",
        "id": "f85d7309-dc8d-4073-ac48-9d3c039814fa",
        "updatedOn": "2025-08-07T11:54:15Z",
        "owner": "85839425-0cfe-471f-94da-e4086b1dc961"
    },
    {
        "supplierType": "gutteringInstall",
        "baseType": "guttering",
        "newBuildings": true,
        "repairReplace": false,
        "hasMinMaxDimensions": false,
        "createdOn": "2025-08-07T11:52:56Z",
        "id": "fb1c6716-de70-44f9-afd6-3098433f265f",
        "updatedOn": "2025-08-07T11:54:15Z",
        "owner": "85839425-0cfe-471f-94da-e4086b1dc961"
    },
    {
        "supplierType": "quantitySurveyorSupplyAndInstall",
        "baseType": "quantitySurveyor",
        "newBuildings": true,
        "repairReplace": false,
        "hasMinMaxDimensions": false,
        "createdOn": "2025-08-07T11:52:56Z",
        "id": "fbf50fd1-ecfe-48f1-b9da-20e1823ae265",
        "updatedOn": "2025-08-07T11:54:15Z",
        "owner": "85839425-0cfe-471f-94da-e4086b1dc961"
    },
    {
        "supplierType": "concreteWallRepairInstall",
        "baseType": "concreteWallRepair",
        "newBuildings": false,
        "repairReplace": true,
        "hasMinMaxDimensions": false,
        "createdOn": "2025-08-07T11:52:56Z",
        "id": "fceeb726-bdd3-4161-8200-4e54e1416098",
        "updatedOn": "2025-08-07T11:54:18Z",
        "owner": "85839425-0cfe-471f-94da-e4086b1dc961"
    },
    {
        "supplierType": "claddingInstall",
        "baseType": "cladding",
        "newBuildings": true,
        "repairReplace": false,
        "hasMinMaxDimensions": false,
        "createdOn": "2025-08-07T11:52:56Z",
        "id": "fedbbd3f-eb66-47b7-944e-749724a3148f",
        "updatedOn": "2025-08-07T11:54:15Z",
        "owner": "85839425-0cfe-471f-94da-e4086b1dc961"
    }
]